quantexa/__init__.py
quantexa/main.py
quantexa-0.1.4.dist-info/METADATA
quantexa-0.1.4.dist-info/WHEEL
quantexa-0.1.4.dist-info/top_level.txt
quantexa-0.1.4.dist-info/RECORD
