Metadata-Version: 2.1
Name: quantexa
Version: 0.1.4
Summary: This is the almighty quantexa package
